webcui/__init__.py
webcui/server.py
webcui-0.1.2.dist-info/LICENSE
webcui-0.1.2.dist-info/METADATA
webcui-0.1.2.dist-info/WHEEL
webcui-0.1.2.dist-info/top_level.txt
webcui-0.1.2.dist-info/RECORD
