Metadata-Version: 2.1
Name: webcui
Version: 0.1.2
Summary: A web command user interface
Home-page: https://gitlab.com/perapp/webcui
Author: Per Appelgren
Author-email: per@appgren.se
License: UNKNOWN
Platform: UNKNOWN
Classifier: Programming Language :: Python :: 3
Classifier: Programming Language :: Python :: 3.6
Classifier: License :: OSI Approved :: GNU General Public License v3 or later (GPLv3+)
Classifier: Operating System :: OS Independent
Requires-Dist: responder
Requires-Dist: pytest
Requires-Dist: selenium
Requires-Dist: pytest-selenium
Requires-Dist: dataclasses
